LICENSE
MANIFEST.in
setup.cfg
setup.py
avatar_field/__init__.py
avatar_field/apps.py
avatar_field/model_fields.py
avatar_field/tests.py
avatar_field/widget.py
avatar_field/static/avatar_field/css/bootstrap.css
avatar_field/static/avatar_field/css/style.css
avatar_field/static/avatar_field/js/bootstrap.min.js
avatar_field/templates/avatar_field/widgets/select.html
avatar_field/templates/avatar_field/widgets/select_option.html
django_avatarfield.egg-info/PKG-INFO
django_avatarfield.egg-info/SOURCES.txt
django_avatarfield.egg-info/dependency_links.txt
django_avatarfield.egg-info/top_level.txt