Metadata-Version: 1.1
Name: django-avatarfield
Version: 0.0.1
Summary: A Django field to help user make avatar field.
Home-page: https://github.com/ZFCon/
Author: Ziad Ahmed
Author-email: ziad32ahmed111@gmail.com
License: MIT License
Platform: UNKNOWN
Classifier: Environment :: Web Environment
Classifier: Framework :: Django
Classifier: Intended Audience :: Developers
Classifier: Operating System :: OS Independent
Classifier: Programming Language :: Python :: 3
Classifier: Topic :: Internet :: WWW/HTTP
Classifier: Topic :: Internet :: WWW/HTTP :: Dynamic Content
